{
 "hexes": {
  "0000": {
   "t": "offmap"
  },
  "0001": {
   "t": "offmap"
  },
  "0002": {
   "t": "offmap"
  },
  "0003": {
   "t": "offmap"
  },
  "0004": {
   "t": "offmap"
  },
  "0005": {
   "t": "offmap"
  },
  "0006": {
   "t": "offmap"
  },
  "0007": {
   "t": "offmap"
  },
  "0008": {
   "t": "offmap"
  },
  "0009": {
   "t": "offmap"
  },
  "0010": {
   "t": "offmap"
  },
  "0011": {
   "t": "offmap"
  },
  "0012": {
   "t": "offmap"
  },
  "0013": {
   "t": "offmap"
  },
  "0014": {
   "t": "offmap"
  },
  "0015": {
   "t": "offmap"
  },
  "0016": {
   "t": "offmap"
  },
  "0017": {
   "t": "offmap"
  },
  "0018": {
   "t": "offmap"
  },
  "0019": {
   "t": "offmap"
  },
  "0020": {
   "t": "offmap"
  },
  "0021": {
   "t": "offmap"
  },
  "0022": {
   "t": "offmap"
  },
  "0023": {
   "t": "offmap"
  },
  "0024": {
   "t": "offmap"
  },
  "0025": {
   "t": "offmap"
  },
  "0026": {
   "t": "offmap"
  },
  "0027": {
   "t": "offmap"
  },
  "0101": {
   "t": "mixed"
  },
  "0102": {
   "t": "mixed"
  },
  "0103": {
   "t": "mixed",
   "road": true
  },
  "0104": {
   "t": "mixed",
   "road": true
  },
  "0105": {
   "t": "town",
   "road": true
  },
  "0106": {
   "t": "town",
   "road": true
  },
  "0107": {
   "t": "mixed"
  },
  "0108": {
   "t": "mixed"
  },
  "0109": {
   "t": "town",
   "road": true
  },
  "0110": {
   "t": "mixed"
  },
  "0111": {
   "t": "broken"
  },
  "0112": {
   "t": "broken"
  },
  "0113": {
   "t": "broken"
  },
  "0114": {
   "t": "broken"
  },
  "0115": {
   "t": "mixed"
  },
  "0116": {
   "t": "mixed"
  },
  "0117": {
   "t": "town"
  },
  "0118": {
   "t": "broken"
  },
  "0119": {
   "t": "broken"
  },
  "0120": {
   "t": "broken"
  },
  "0121": {
   "t": "mixed"
  },
  "0122": {
   "t": "mixed"
  },
  "0123": {
   "t": "mixed"
  },
  "0124": {
   "t": "mixed"
  },
  "0125": {
   "t": "mixed"
  },
  "0126": {
   "t": "mixed"
  },
  "0127": {
   "t": "offmap"
  },
  "0200": {
   "t": "offmap"
  },
  "0201": {
   "t": "mixed"
  },
  "0202": {
   "t": "mixed"
  },
  "0203": {
   "t": "city"
  },
  "0204": {
   "t": "city",
   "road": true
  },
  "0205": {
   "t": "mixed"
  },
  "0206": {
   "t": "mixed",
   "road": true
  },
  "0207": {
   "t": "mixed"
  },
  "0208": {
   "t": "mixed"
  },
  "0209": {
   "t": "town",
   "road": true
  },
  "0210": {
   "t": "broken"
  },
  "0211": {
   "t": "broken"
  },
  "0212": {
   "t": "broken"
  },
  "0213": {
   "t": "mixed"
  },
  "0214": {
   "t": "town"
  },
  "0215": {
   "t": "town"
  },
  "0216": {
   "t": "town"
  },
  "0217": {
   "t": "mixed"
  },
  "0218": {
   "t": "broken"
  },
  "0219": {
   "t": "mixed"
  },
  "0220": {
   "t": "mixed"
  },
  "0221": {
   "t": "mixed"
  },
  "0222": {
   "t": "mixed"
  },
  "0223": {
   "t": "mixed"
  },
  "0224": {
   "t": "mixed"
  },
  "0225": {
   "t": "mixed"
  },
  "0226": {
   "t": "offmap"
  },
  "0227": {
   "t": "offmap"
  },
  "0301": {
   "t": "mixed"
  },
  "0302": {
   "t": "mixed"
  },
  "0303": {
   "t": "mixed"
  },
  "0304": {
   "t": "city",
   "road": true
  },
  "0305": {
   "t": "mixed"
  },
  "0306": {
   "t": "mixed"
  },
  "0307": {
   "t": "town",
   "road": true
  },
  "0308": {
   "t": "mixed",
   "road": true
  },
  "0309": {
   "t": "town",
   "road": true
  },
  "0310": {
   "t": "town",
   "road": true
  },
  "0311": {
   "t": "town"
  },
  "0312": {
   "t": "town",
   "road": true
  },
  "0313": {
   "t": "broken"
  },
  "0314": {
   "t": "mixed"
  },
  "0315": {
   "t": "mixed"
  },
  "0316": {
   "t": "mixed"
  },
  "0317": {
   "t": "mixed"
  },
  "0318": {
   "t": "broken"
  },
  "0319": {
   "t": "town",
   "road": true
  },
  "0320": {
   "t": "mixed"
  },
  "0321": {
   "t": "broken"
  },
  "0322": {
   "t": "mixed"
  },
  "0323": {
   "t": "mixed"
  },
  "0324": {
   "t": "mixed"
  },
  "0325": {
   "t": "mixed"
  },
  "0326": {
   "t": "mixed"
  },
  "0327": {
   "t": "offmap"
  },
  "0400": {
   "t": "offmap"
  },
  "0401": {
   "t": "mixed"
  },
  "0402": {
   "t": "mixed"
  },
  "0403": {
   "t": "town",
   "road": true
  },
  "0404": {
   "t": "town",
   "road": true
  },
  "0405": {
   "t": "mixed"
  },
  "0406": {
   "t": "mixed"
  },
  "0407": {
   "t": "town",
   "road": true
  },
  "0408": {
   "t": "mixed"
  },
  "0409": {
   "t": "mixed"
  },
  "0410": {
   "t": "broken"
  },
  "0411": {
   "t": "broken"
  },
  "0412": {
   "t": "broken"
  },
  "0413": {
   "t": "mixed",
   "road": true
  },
  "0414": {
   "t": "town"
  },
  "0415": {
   "t": "town",
   "road": true
  },
  "0416": {
   "t": "mixed"
  },
  "0417": {
   "t": "broken"
  },
  "0418": {
   "t": "broken"
  },
  "0419": {
   "t": "mixed"
  },
  "0420": {
   "t": "broken"
  },
  "0421": {
   "t": "town",
   "road": true
  },
  "0422": {
   "t": "mixed"
  },
  "0423": {
   "t": "mixed"
  },
  "0424": {
   "t": "mixed"
  },
  "0425": {
   "t": "mixed"
  },
  "0426": {
   "t": "offmap"
  },
  "0427": {
   "t": "offmap"
  },
  "0501": {
   "t": "mixed"
  },
  "0502": {
   "t": "mixed"
  },
  "0503": {
   "t": "town",
   "road": true
  },
  "0504": {
   "t": "mixed"
  },
  "0505": {
   "t": "town",
   "road": true
  },
  "0506": {
   "t": "mixed"
  },
  "0507": {
   "t": "mixed",
   "road": true
  },
  "0508": {
   "t": "mixed",
   "road": true
  },
  "0509": {
   "t": "mixed"
  },
  "0510": {
   "t": "mixed"
  },
  "0511": {
   "t": "broken"
  },
  "0512": {
   "t": "mixed"
  },
  "0513": {
   "t": "mixed"
  },
  "0514": {
   "t": "mixed"
  },
  "0515": {
   "t": "mixed"
  },
  "0516": {
   "t": "mixed"
  },
  "0517": {
   "t": "broken"
  },
  "0518": {
   "t": "broken"
  },
  "0519": {
   "t": "broken"
  },
  "0520": {
   "t": "broken"
  },
  "0521": {
   "t": "broken"
  },
  "0522": {
   "t": "mixed"
  },
  "0523": {
   "t": "town",
   "road": true
  },
  "0524": {
   "t": "mixed"
  },
  "0525": {
   "t": "mixed"
  },
  "0526": {
   "t": "mixed"
  },
  "0527": {
   "t": "offmap"
  },
  "0600": {
   "t": "offmap"
  },
  "0601": {
   "t": "mixed"
  },
  "0602": {
   "t": "town"
  },
  "0603": {
   "t": "woods"
  },
  "0604": {
   "t": "woods"
  },
  "0605": {
   "t": "woods",
   "road": true
  },
  "0606": {
   "t": "broken",
   "road": true
  },
  "0607": {
   "t": "broken"
  },
  "0608": {
   "t": "mixed"
  },
  "0609": {
   "t": "mixed"
  },
  "0610": {
   "t": "broken"
  },
  "0611": {
   "t": "broken"
  },
  "0612": {
   "t": "mixed"
  },
  "0613": {
   "t": "mixed",
   "road": true
  },
  "0614": {
   "t": "mixed"
  },
  "0615": {
   "t": "mixed"
  },
  "0616": {
   "t": "town"
  },
  "0617": {
   "t": "broken"
  },
  "0618": {
   "t": "broken"
  },
  "0619": {
   "t": "broken"
  },
  "0620": {
   "t": "broken"
  },
  "0621": {
   "t": "mixed"
  },
  "0622": {
   "t": "town"
  },
  "0623": {
   "t": "town"
  },
  "0624": {
   "t": "mixed"
  },
  "0625": {
   "t": "mixed"
  },
  "0626": {
   "t": "offmap"
  },
  "0627": {
   "t": "offmap"
  },
  "0701": {
   "t": "town",
   "road": true
  },
  "0702": {
   "t": "town"
  },
  "0703": {
   "t": "broken"
  },
  "0704": {
   "t": "woods"
  },
  "0705": {
   "t": "woods"
  },
  "0706": {
   "t": "woods"
  },
  "0707": {
   "t": "broken"
  },
  "0708": {
   "t": "broken",
   "road": true
  },
  "0709": {
   "t": "mixed"
  },
  "0710": {
   "t": "town"
  },
  "0711": {
   "t": "broken"
  },
  "0712": {
   "t": "mixed"
  },
  "0713": {
   "t": "mixed"
  },
  "0714": {
   "t": "broken"
  },
  "0715": {
   "t": "mixed"
  },
  "0716": {
   "t": "mixed"
  },
  "0717": {
   "t": "mixed"
  },
  "0718": {
   "t": "broken"
  },
  "0719": {
   "t": "broken"
  },
  "0720": {
   "t": "broken"
  },
  "0721": {
   "t": "mixed"
  },
  "0722": {
   "t": "mixed"
  },
  "0723": {
   "t": "mixed"
  },
  "0724": {
   "t": "mixed"
  },
  "0725": {
   "t": "mixed"
  },
  "0726": {
   "t": "town"
  },
  "0727": {
   "t": "offmap"
  },
  "0800": {
   "t": "offmap"
  },
  "0801": {
   "t": "town",
   "road": true
  },
  "0802": {
   "t": "broken",
   "road": true
  },
  "0803": {
   "t": "broken"
  },
  "0804": {
   "t": "broken"
  },
  "0805": {
   "t": "town",
   "road": true
  },
  "0806": {
   "t": "broken"
  },
  "0807": {
   "t": "mixed"
  },
  "0808": {
   "t": "mixed"
  },
  "0809": {
   "t": "mixed"
  },
  "0810": {
   "t": "broken"
  },
  "0811": {
   "t": "broken"
  },
  "0812": {
   "t": "town",
   "road": true
  },
  "0813": {
   "t": "mixed"
  },
  "0814": {
   "t": "broken"
  },
  "0815": {
   "t": "broken"
  },
  "0816": {
   "t": "mixed"
  },
  "0817": {
   "t": "town",
   "road": true
  },
  "0818": {
   "t": "broken"
  },
  "0819": {
   "t": "broken"
  },
  "0820": {
   "t": "broken"
  },
  "0821": {
   "t": "mixed"
  },
  "0822": {
   "t": "mixed"
  },
  "0823": {
   "t": "mixed"
  },
  "0824": {
   "t": "mixed"
  },
  "0825": {
   "t": "mixed"
  },
  "0826": {
   "t": "offmap"
  },
  "0827": {
   "t": "offmap"
  },
  "0901": {
   "t": "town",
   "road": true
  },
  "0902": {
   "t": "mixed"
  },
  "0903": {
   "t": "broken",
   "road": true
  },
  "0904": {
   "t": "broken"
  },
  "0905": {
   "t": "town",
   "road": true
  },
  "0906": {
   "t": "broken"
  },
  "0907": {
   "t": "mixed"
  },
  "0908": {
   "t": "mixed"
  },
  "0909": {
   "t": "mixed"
  },
  "0910": {
   "t": "broken"
  },
  "0911": {
   "t": "broken"
  },
  "0912": {
   "t": "broken"
  },
  "0913": {
   "t": "mixed"
  },
  "0914": {
   "t": "mixed",
   "road": true
  },
  "0915": {
   "t": "broken",
   "road": true
  },
  "0916": {
   "t": "town",
   "road": true
  },
  "0917": {
   "t": "broken"
  },
  "0918": {
   "t": "broken"
  },
  "0919": {
   "t": "broken"
  },
  "0920": {
   "t": "town"
  },
  "0921": {
   "t": "broken"
  },
  "0922": {
   "t": "mixed"
  },
  "0923": {
   "t": "mixed"
  },
  "0924": {
   "t": "mixed"
  },
  "0925": {
   "t": "mixed"
  },
  "0926": {
   "t": "town",
   "road": true
  },
  "0927": {
   "t": "offmap"
  },
  "1000": {
   "t": "offmap"
  },
  "1001": {
   "t": "mixed"
  },
  "1002": {
   "t": "mixed"
  },
  "1003": {
   "t": "mixed",
   "road": true
  },
  "1004": {
   "t": "town",
   "road": true
  },
  "1005": {
   "t": "mixed"
  },
  "1006": {
   "t": "mixed"
  },
  "1007": {
   "t": "mixed"
  },
  "1008": {
   "t": "mixed"
  },
  "1009": {
   "t": "broken"
  },
  "1010": {
   "t": "broken"
  },
  "1011": {
   "t": "town",
   "road": true
  },
  "1012": {
   "t": "mixed"
  },
  "1013": {
   "t": "mixed"
  },
  "1014": {
   "t": "broken"
  },
  "1015": {
   "t": "broken"
  },
  "1016": {
   "t": "mixed"
  },
  "1017": {
   "t": "broken",
   "road": true
  },
  "1018": {
   "t": "town",
   "road": true
  },
  "1019": {
   "t": "town"
  },
  "1020": {
   "t": "broken"
  },
  "1021": {
   "t": "broken"
  },
  "1022": {
   "t": "mixed"
  },
  "1023": {
   "t": "mixed"
  },
  "1024": {
   "t": "mixed"
  },
  "1025": {
   "t": "town"
  },
  "1026": {
   "t": "offmap"
  },
  "1027": {
   "t": "offmap"
  },
  "1101": {
   "t": "mixed"
  },
  "1102": {
   "t": "mixed"
  },
  "1103": {
   "t": "mixed",
   "road": true
  },
  "1104": {
   "t": "mixed"
  },
  "1105": {
   "t": "mixed"
  },
  "1106": {
   "t": "town",
   "road": true
  },
  "1107": {
   "t": "mixed"
  },
  "1108": {
   "t": "broken"
  },
  "1109": {
   "t": "broken"
  },
  "1110": {
   "t": "mixed"
  },
  "1111": {
   "t": "mixed"
  },
  "1112": {
   "t": "mixed"
  },
  "1113": {
   "t": "mixed"
  },
  "1114": {
   "t": "broken"
  },
  "1115": {
   "t": "broken"
  },
  "1116": {
   "t": "mixed"
  },
  "1117": {
   "t": "mixed"
  },
  "1118": {
   "t": "broken"
  },
  "1119": {
   "t": "town"
  },
  "1120": {
   "t": "town",
   "road": true
  },
  "1121": {
   "t": "mixed"
  },
  "1122": {
   "t": "broken"
  },
  "1123": {
   "t": "mixed"
  },
  "1124": {
   "t": "mixed"
  },
  "1125": {
   "t": "town"
  },
  "1126": {
   "t": "mixed"
  },
  "1127": {
   "t": "offmap"
  },
  "1200": {
   "t": "offmap"
  },
  "1201": {
   "t": "mixed"
  },
  "1202": {
   "t": "mixed"
  },
  "1203": {
   "t": "mixed"
  },
  "1204": {
   "t": "town"
  },
  "1205": {
   "t": "mixed"
  },
  "1206": {
   "t": "town",
   "road": true
  },
  "1207": {
   "t": "mixed"
  },
  "1208": {
   "t": "broken"
  },
  "1209": {
   "t": "town",
   "road": true
  },
  "1210": {
   "t": "mixed"
  },
  "1211": {
   "t": "mixed"
  },
  "1212": {
   "t": "mixed"
  },
  "1213": {
   "t": "broken"
  },
  "1214": {
   "t": "broken"
  },
  "1215": {
   "t": "broken"
  },
  "1216": {
   "t": "broken"
  },
  "1217": {
   "t": "broken"
  },
  "1218": {
   "t": "mixed"
  },
  "1219": {
   "t": "town"
  },
  "1220": {
   "t": "mixed"
  },
  "1221": {
   "t": "mixed"
  },
  "1222": {
   "t": "mixed"
  },
  "1223": {
   "t": "mixed"
  },
  "1224": {
   "t": "town"
  },
  "1225": {
   "t": "mixed"
  },
  "1226": {
   "t": "offmap"
  },
  "1227": {
   "t": "offmap"
  },
  "1301": {
   "t": "mixed"
  },
  "1302": {
   "t": "mixed"
  },
  "1303": {
   "t": "mixed"
  },
  "1304": {
   "t": "mixed",
   "road": true
  },
  "1305": {
   "t": "town"
  },
  "1306": {
   "t": "mixed"
  },
  "1307": {
   "t": "mixed"
  },
  "1308": {
   "t": "town",
   "road": true
  },
  "1309": {
   "t": "town",
   "road": true
  },
  "1310": {
   "t": "mixed"
  },
  "1311": {
   "t": "mixed"
  },
  "1312": {
   "t": "mixed"
  },
  "1313": {
   "t": "mixed"
  },
  "1314": {
   "t": "mixed"
  },
  "1315": {
   "t": "broken"
  },
  "1316": {
   "t": "broken"
  },
  "1317": {
   "t": "woods"
  },
  "1318": {
   "t": "mixed"
  },
  "1319": {
   "t": "town"
  },
  "1320": {
   "t": "mixed"
  },
  "1321": {
   "t": "mixed"
  },
  "1322": {
   "t": "town"
  },
  "1323": {
   "t": "mixed"
  },
  "1324": {
   "t": "town"
  },
  "1325": {
   "t": "mixed"
  },
  "1326": {
   "t": "mixed"
  },
  "1327": {
   "t": "offmap"
  },
  "1400": {
   "t": "offmap"
  },
  "1401": {
   "t": "mixed"
  },
  "1402": {
   "t": "mixed"
  },
  "1403": {
   "t": "mixed",
   "road": true
  },
  "1404": {
   "t": "mixed"
  },
  "1405": {
   "t": "broken"
  },
  "1406": {
   "t": "mixed"
  },
  "1407": {
   "t": "mixed",
   "road": true
  },
  "1408": {
   "t": "mixed"
  },
  "1409": {
   "t": "town",
   "road": true
  },
  "1410": {
   "t": "mixed"
  },
  "1411": {
   "t": "mixed",
   "road": true
  },
  "1412": {
   "t": "town",
   "road": true
  },
  "1413": {
   "t": "mixed",
   "road": true
  },
  "1414": {
   "t": "mixed"
  },
  "1415": {
   "t": "broken"
  },
  "1416": {
   "t": "woods"
  },
  "1417": {
   "t": "mixed"
  },
  "1418": {
   "t": "mixed"
  },
  "1419": {
   "t": "mixed"
  },
  "1420": {
   "t": "mixed"
  },
  "1421": {
   "t": "mixed"
  },
  "1422": {
   "t": "mixed"
  },
  "1423": {
   "t": "town"
  },
  "1424": {
   "t": "mixed"
  },
  "1425": {
   "t": "mixed"
  },
  "1426": {
   "t": "offmap"
  },
  "1427": {
   "t": "offmap"
  },
  "1501": {
   "t": "mixed"
  },
  "1502": {
   "t": "mixed"
  },
  "1503": {
   "t": "broken",
   "road": true
  },
  "1504": {
   "t": "broken"
  },
  "1505": {
   "t": "mixed"
  },
  "1506": {
   "t": "mixed",
   "road": true
  },
  "1507": {
   "t": "mixed"
  },
  "1508": {
   "t": "mixed"
  },
  "1509": {
   "t": "mixed"
  },
  "1510": {
   "t": "mixed"
  },
  "1511": {
   "t": "town",
   "road": true
  },
  "1512": {
   "t": "mixed"
  },
  "1513": {
   "t": "mixed"
  },
  "1514": {
   "t": "mixed"
  },
  "1515": {
   "t": "broken"
  },
  "1516": {
   "t": "town"
  },
  "1517": {
   "t": "town",
   "road": true
  },
  "1518": {
   "t": "town"
  },
  "1519": {
   "t": "town",
   "road": true
  },
  "1520": {
   "t": "mixed"
  },
  "1521": {
   "t": "mixed"
  },
  "1522": {
   "t": "broken"
  },
  "1523": {
   "t": "mixed"
  },
  "1524": {
   "t": "mixed"
  },
  "1525": {
   "t": "mixed"
  },
  "1526": {
   "t": "mixed"
  },
  "1527": {
   "t": "offmap"
  },
  "1600": {
   "t": "offmap"
  },
  "1601": {
   "t": "mixed"
  },
  "1602": {
   "t": "mixed"
  },
  "1603": {
   "t": "broken"
  },
  "1604": {
   "t": "mixed",
   "road": true
  },
  "1605": {
   "t": "mixed"
  },
  "1606": {
   "t": "mixed"
  },
  "1607": {
   "t": "mixed"
  },
  "1608": {
   "t": "mixed"
  },
  "1609": {
   "t": "mixed"
  },
  "1610": {
   "t": "mixed",
   "road": true
  },
  "1611": {
   "t": "mixed",
   "road": true
  },
  "1612": {
   "t": "mixed"
  },
  "1613": {
   "t": "mixed"
  },
  "1614": {
   "t": "mixed"
  },
  "1615": {
   "t": "mixed"
  },
  "1616": {
   "t": "town"
  },
  "1617": {
   "t": "mixed"
  },
  "1618": {
   "t": "broken"
  },
  "1619": {
   "t": "broken"
  },
  "1620": {
   "t": "mixed"
  },
  "1621": {
   "t": "mixed"
  },
  "1622": {
   "t": "mixed"
  },
  "1623": {
   "t": "town",
   "road": true
  },
  "1624": {
   "t": "mixed"
  },
  "1625": {
   "t": "mixed"
  },
  "1626": {
   "t": "offmap"
  },
  "1627": {
   "t": "offmap"
  },
  "1701": {
   "t": "mixed"
  },
  "1702": {
   "t": "mixed"
  },
  "1703": {
   "t": "broken"
  },
  "1704": {
   "t": "mixed",
   "road": true
  },
  "1705": {
   "t": "mixed"
  },
  "1706": {
   "t": "mixed"
  },
  "1707": {
   "t": "mixed"
  },
  "1708": {
   "t": "mixed"
  },
  "1709": {
   "t": "mixed"
  },
  "1710": {
   "t": "mixed",
   "road": true
  },
  "1711": {
   "t": "mixed"
  },
  "1712": {
   "t": "mixed"
  },
  "1713": {
   "t": "town",
   "road": true
  },
  "1714": {
   "t": "mixed",
   "road": true
  },
  "1715": {
   "t": "mixed"
  },
  "1716": {
   "t": "mixed"
  },
  "1717": {
   "t": "mixed"
  },
  "1718": {
   "t": "mixed"
  },
  "1719": {
   "t": "mixed"
  },
  "1720": {
   "t": "town"
  },
  "1721": {
   "t": "mixed"
  },
  "1722": {
   "t": "mixed"
  },
  "1723": {
   "t": "town",
   "road": true
  },
  "1724": {
   "t": "mixed"
  },
  "1725": {
   "t": "mixed"
  },
  "1726": {
   "t": "mixed"
  },
  "1727": {
   "t": "offmap"
  },
  "1800": {
   "t": "offmap"
  },
  "1801": {
   "t": "mixed"
  },
  "1802": {
   "t": "broken",
   "road": true
  },
  "1803": {
   "t": "mixed"
  },
  "1804": {
   "t": "mixed"
  },
  "1805": {
   "t": "mixed"
  },
  "1806": {
   "t": "mixed"
  },
  "1807": {
   "t": "woods"
  },
  "1808": {
   "t": "mixed"
  },
  "1809": {
   "t": "town",
   "road": true
  },
  "1810": {
   "t": "mixed"
  },
  "1811": {
   "t": "woods"
  },
  "1812": {
   "t": "broken"
  },
  "1813": {
   "t": "mixed",
   "road": true
  },
  "1814": {
   "t": "mixed"
  },
  "1815": {
   "t": "mixed",
   "road": true
  },
  "1816": {
   "t": "mixed"
  },
  "1817": {
   "t": "mixed",
   "road": true
  },
  "1818": {
   "t": "mixed",
   "road": true
  },
  "1819": {
   "t": "mixed"
  },
  "1820": {
   "t": "mixed"
  },
  "1821": {
   "t": "mixed"
  },
  "1822": {
   "t": "town",
   "road": true
  },
  "1823": {
   "t": "mixed"
  },
  "1824": {
   "t": "mixed"
  },
  "1825": {
   "t": "mixed"
  },
  "1826": {
   "t": "offmap"
  },
  "1827": {
   "t": "offmap"
  },
  "1901": {
   "t": "town",
   "road": true
  },
  "1902": {
   "t": "mixed",
   "road": true
  },
  "1903": {
   "t": "mixed"
  },
  "1904": {
   "t": "mixed"
  },
  "1905": {
   "t": "mixed"
  },
  "1906": {
   "t": "mixed"
  },
  "1907": {
   "t": "woods"
  },
  "1908": {
   "t": "woods"
  },
  "1909": {
   "t": "mixed",
   "road": true
  },
  "1910": {
   "t": "woods"
  },
  "1911": {
   "t": "woods"
  },
  "1912": {
   "t": "woods"
  },
  "1913": {
   "t": "mixed"
  },
  "1914": {
   "t": "mixed",
   "road": true
  },
  "1915": {
   "t": "woods"
  },
  "1916": {
   "t": "mixed",
   "road": true
  },
  "1917": {
   "t": "mixed",
   "road": true
  },
  "1918": {
   "t": "mixed"
  },
  "1919": {
   "t": "mixed"
  },
  "1920": {
   "t": "mixed"
  },
  "1921": {
   "t": "town"
  },
  "1922": {
   "t": "woods"
  },
  "1923": {
   "t": "rough"
  },
  "1924": {
   "t": "broken"
  },
  "1925": {
   "t": "broken"
  },
  "1926": {
   "t": "woods"
  },
  "1927": {
   "t": "offmap"
  },
  "2000": {
   "t": "offmap"
  },
  "2001": {
   "t": "mixed"
  },
  "2002": {
   "t": "broken"
  },
  "2003": {
   "t": "broken",
   "road": true
  },
  "2004": {
   "t": "mixed",
   "road": true
  },
  "2005": {
   "t": "mixed",
   "road": true
  },
  "2006": {
   "t": "mixed"
  },
  "2007": {
   "t": "mixed",
   "road": true
  },
  "2008": {
   "t": "mixed",
   "road": true
  },
  "2009": {
   "t": "mixed",
   "road": true
  },
  "2010": {
   "t": "woods"
  },
  "2011": {
   "t": "mixed",
   "road": true
  },
  "2012": {
   "t": "mixed",
   "road": true
  },
  "2013": {
   "t": "mixed",
   "road": true
  },
  "2014": {
   "t": "mixed",
   "road": true
  },
  "2015": {
   "t": "town",
   "road": true
  },
  "2016": {
   "t": "mixed",
   "road": true
  },
  "2017": {
   "t": "mixed"
  },
  "2018": {
   "t": "mixed"
  },
  "2019": {
   "t": "mixed"
  },
  "2020": {
   "t": "mixed",
   "road": true
  },
  "2021": {
   "t": "rough"
  },
  "2022": {
   "t": "broken"
  },
  "2023": {
   "t": "broken",
   "road": true
  },
  "2024": {
   "t": "mixed"
  },
  "2025": {
   "t": "broken"
  },
  "2026": {
   "t": "offmap"
  },
  "2027": {
   "t": "offmap"
  },
  "2101": {
   "t": "broken"
  },
  "2102": {
   "t": "mixed"
  },
  "2103": {
   "t": "broken"
  },
  "2104": {
   "t": "broken"
  },
  "2105": {
   "t": "mixed"
  },
  "2106": {
   "t": "mixed"
  },
  "2107": {
   "t": "mixed"
  },
  "2108": {
   "t": "mixed"
  },
  "2109": {
   "t": "mixed",
   "road": true
  },
  "2110": {
   "t": "woods"
  },
  "2111": {
   "t": "woods"
  },
  "2112": {
   "t": "mixed"
  },
  "2113": {
   "t": "mixed"
  },
  "2114": {
   "t": "mixed",
   "road": true
  },
  "2115": {
   "t": "mixed",
   "road": true
  },
  "2116": {
   "t": "town",
   "road": true
  },
  "2117": {
   "t": "mixed"
  },
  "2118": {
   "t": "mixed"
  },
  "2119": {
   "t": "mixed",
   "road": true
  },
  "2120": {
   "t": "town"
  },
  "2121": {
   "t": "mixed",
   "road": true
  },
  "2122": {
   "t": "woods"
  },
  "2123": {
   "t": "rough",
   "road": true
  },
  "2124": {
   "t": "mixed"
  },
  "2125": {
   "t": "mixed"
  },
  "2126": {
   "t": "woods"
  },
  "2127": {
   "t": "offmap"
  },
  "2200": {
   "t": "offmap"
  },
  "2201": {
   "t": "broken",
   "road": true
  },
  "2202": {
   "t": "broken"
  },
  "2203": {
   "t": "broken"
  },
  "2204": {
   "t": "broken"
  },
  "2205": {
   "t": "broken"
  },
  "2206": {
   "t": "broken"
  },
  "2207": {
   "t": "mixed"
  },
  "2208": {
   "t": "town"
  },
  "2209": {
   "t": "mixed"
  },
  "2210": {
   "t": "woods"
  },
  "2211": {
   "t": "town",
   "road": true
  },
  "2212": {
   "t": "mixed",
   "road": true
  },
  "2213": {
   "t": "mixed",
   "road": true
  },
  "2214": {
   "t": "mixed"
  },
  "2215": {
   "t": "town",
   "road": true
  },
  "2216": {
   "t": "mixed"
  },
  "2217": {
   "t": "town",
   "road": true
  },
  "2218": {
   "t": "mixed"
  },
  "2219": {
   "t": "mixed",
   "road": true
  },
  "2220": {
   "t": "town"
  },
  "2221": {
   "t": "woods"
  },
  "2222": {
   "t": "rough"
  },
  "2223": {
   "t": "town"
  },
  "2224": {
   "t": "mixed"
  },
  "2225": {
   "t": "woods"
  },
  "2226": {
   "t": "offmap"
  },
  "2227": {
   "t": "offmap"
  },
  "2301": {
   "t": "mixed"
  },
  "2302": {
   "t": "broken",
   "road": true
  },
  "2303": {
   "t": "broken"
  },
  "2304": {
   "t": "broken"
  },
  "2305": {
   "t": "broken"
  },
  "2306": {
   "t": "broken"
  },
  "2307": {
   "t": "mixed"
  },
  "2308": {
   "t": "mixed",
   "road": true
  },
  "2309": {
   "t": "mixed"
  },
  "2310": {
   "t": "mixed",
   "road": true
  },
  "2311": {
   "t": "mixed",
   "road": true
  },
  "2312": {
   "t": "mixed"
  },
  "2313": {
   "t": "broken",
   "road": true
  },
  "2314": {
   "t": "broken"
  },
  "2315": {
   "t": "broken"
  },
  "2316": {
   "t": "broken",
   "road": true
  },
  "2317": {
   "t": "woods"
  },
  "2318": {
   "t": "mixed",
   "road": true
  },
  "2319": {
   "t": "mixed",
   "road": true
  },
  "2320": {
   "t": "mixed"
  },
  "2321": {
   "t": "woods"
  },
  "2322": {
   "t": "rough"
  },
  "2323": {
   "t": "rough",
   "road": true
  },
  "2324": {
   "t": "town",
   "road": true
  },
  "2325": {
   "t": "town",
   "road": true
  },
  "2326": {
   "t": "woods"
  },
  "2327": {
   "t": "offmap"
  },
  "2400": {
   "t": "offmap"
  },
  "2401": {
   "t": "mixed"
  },
  "2402": {
   "t": "broken",
   "road": true
  },
  "2403": {
   "t": "broken",
   "road": true
  },
  "2404": {
   "t": "broken"
  },
  "2405": {
   "t": "broken"
  },
  "2406": {
   "t": "broken"
  },
  "2407": {
   "t": "mixed",
   "road": true
  },
  "2408": {
   "t": "broken"
  },
  "2409": {
   "t": "mixed"
  },
  "2410": {
   "t": "broken"
  },
  "2411": {
   "t": "broken"
  },
  "2412": {
   "t": "broken",
   "road": true
  },
  "2413": {
   "t": "mixed"
  },
  "2414": {
   "t": "broken",
   "road": true
  },
  "2415": {
   "t": "town",
   "road": true
  },
  "2416": {
   "t": "woods"
  },
  "2417": {
   "t": "mixed"
  },
  "2418": {
   "t": "mixed"
  },
  "2419": {
   "t": "woods"
  },
  "2420": {
   "t": "woods"
  },
  "2421": {
   "t": "rough"
  },
  "2422": {
   "t": "rough"
  },
  "2423": {
   "t": "town",
   "road": true
  },
  "2424": {
   "t": "mixed",
   "road": true
  },
  "2425": {
   "t": "mixed"
  },
  "2426": {
   "t": "offmap"
  },
  "2427": {
   "t": "offmap"
  },
  "2501": {
   "t": "offmap"
  },
  "2502": {
   "t": "offmap"
  },
  "2503": {
   "t": "mixed"
  },
  "2504": {
   "t": "broken",
   "road": true
  },
  "2505": {
   "t": "broken",
   "road": true
  },
  "2506": {
   "t": "broken",
   "road": true
  },
  "2507": {
   "t": "town",
   "road": true
  },
  "2508": {
   "t": "town",
   "road": true
  },
  "2509": {
   "t": "broken",
   "road": true
  },
  "2510": {
   "t": "broken",
   "road": true
  },
  "2511": {
   "t": "broken"
  },
  "2512": {
   "t": "broken"
  },
  "2513": {
   "t": "mixed"
  },
  "2514": {
   "t": "mixed"
  },
  "2515": {
   "t": "town",
   "road": true
  },
  "2516": {
   "t": "broken"
  },
  "2517": {
   "t": "woods"
  },
  "2518": {
   "t": "town"
  },
  "2519": {
   "t": "town",
   "road": true
  },
  "2520": {
   "t": "city",
   "road": true
  },
  "2521": {
   "t": "city",
   "road": true
  },
  "2522": {
   "t": "rough"
  },
  "2523": {
   "t": "town",
   "road": true
  },
  "2524": {
   "t": "mixed"
  },
  "2525": {
   "t": "mixed"
  },
  "2526": {
   "t": "mixed"
  },
  "2527": {
   "t": "offmap"
  },
  "2600": {
   "t": "offmap"
  },
  "2601": {
   "t": "offmap"
  },
  "2602": {
   "t": "offmap"
  },
  "2603": {
   "t": "mixed"
  },
  "2604": {
   "t": "broken"
  },
  "2605": {
   "t": "mixed"
  },
  "2606": {
   "t": "mixed"
  },
  "2607": {
   "t": "broken"
  },
  "2608": {
   "t": "mixed",
   "road": true
  },
  "2609": {
   "t": "mixed"
  },
  "2610": {
   "t": "broken"
  },
  "2611": {
   "t": "broken"
  },
  "2612": {
   "t": "mixed",
   "road": true
  },
  "2613": {
   "t": "mixed"
  },
  "2614": {
   "t": "town"
  },
  "2615": {
   "t": "broken"
  },
  "2616": {
   "t": "broken"
  },
  "2617": {
   "t": "broken"
  },
  "2618": {
   "t": "broken"
  },
  "2619": {
   "t": "town"
  },
  "2620": {
   "t": "city",
   "road": true
  },
  "2621": {
   "t": "city",
   "road": true
  },
  "2622": {
   "t": "mixed"
  },
  "2623": {
   "t": "town"
  },
  "2624": {
   "t": "mixed"
  },
  "2625": {
   "t": "mixed"
  },
  "2626": {
   "t": "offmap"
  },
  "2627": {
   "t": "offmap"
  },
  "2701": {
   "t": "offmap"
  },
  "2702": {
   "t": "offmap"
  },
  "2703": {
   "t": "offmap"
  },
  "2704": {
   "t": "broken"
  },
  "2705": {
   "t": "broken"
  },
  "2706": {
   "t": "broken"
  },
  "2707": {
   "t": "mixed"
  },
  "2708": {
   "t": "mixed",
   "road": true
  },
  "2709": {
   "t": "broken"
  },
  "2710": {
   "t": "mixed"
  },
  "2711": {
   "t": "town",
   "road": true
  },
  "2712": {
   "t": "broken"
  },
  "2713": {
   "t": "broken"
  },
  "2714": {
   "t": "mixed"
  },
  "2715": {
   "t": "mixed"
  },
  "2716": {
   "t": "broken"
  },
  "2717": {
   "t": "mixed"
  },
  "2718": {
   "t": "mixed"
  },
  "2719": {
   "t": "town"
  },
  "2720": {
   "t": "mixed"
  },
  "2721": {
   "t": "town",
   "road": true
  },
  "2722": {
   "t": "mixed"
  },
  "2723": {
   "t": "mixed"
  },
  "2724": {
   "t": "mixed"
  },
  "2725": {
   "t": "mixed"
  },
  "2726": {
   "t": "mixed"
  },
  "2727": {
   "t": "offmap"
  },
  "2800": {
   "t": "offmap"
  },
  "2801": {
   "t": "offmap"
  },
  "2802": {
   "t": "offmap"
  },
  "2803": {
   "t": "mixed"
  },
  "2804": {
   "t": "mixed"
  },
  "2805": {
   "t": "broken"
  },
  "2806": {
   "t": "broken"
  },
  "2807": {
   "t": "broken"
  },
  "2808": {
   "t": "broken"
  },
  "2809": {
   "t": "mixed"
  },
  "2810": {
   "t": "mixed"
  },
  "2811": {
   "t": "broken"
  },
  "2812": {
   "t": "broken"
  },
  "2813": {
   "t": "broken"
  },
  "2814": {
   "t": "broken"
  },
  "2815": {
   "t": "broken"
  },
  "2816": {
   "t": "town"
  },
  "2817": {
   "t": "mixed"
  },
  "2818": {
   "t": "mixed"
  },
  "2819": {
   "t": "mixed"
  },
  "2820": {
   "t": "town",
   "road": true
  },
  "2821": {
   "t": "town",
   "road": true
  },
  "2822": {
   "t": "mixed"
  },
  "2823": {
   "t": "mixed"
  },
  "2824": {
   "t": "mixed"
  },
  "2825": {
   "t": "mixed"
  },
  "2826": {
   "t": "offmap"
  },
  "2827": {
   "t": "offmap"
  },
  "2901": {
   "t": "offmap"
  },
  "2902": {
   "t": "offmap"
  },
  "2903": {
   "t": "offmap"
  },
  "2904": {
   "t": "offmap"
  },
  "2905": {
   "t": "offmap"
  },
  "2906": {
   "t": "broken"
  },
  "2907": {
   "t": "broken"
  },
  "2908": {
   "t": "broken"
  },
  "2909": {
   "t": "broken"
  },
  "2910": {
   "t": "broken"
  },
  "2911": {
   "t": "broken"
  },
  "2912": {
   "t": "broken"
  },
  "2913": {
   "t": "broken"
  },
  "2914": {
   "t": "broken"
  },
  "2915": {
   "t": "town"
  },
  "2916": {
   "t": "broken"
  },
  "2917": {
   "t": "woods"
  },
  "2918": {
   "t": "woods"
  },
  "2919": {
   "t": "broken",
   "road": true
  },
  "2920": {
   "t": "town",
   "road": true
  },
  "2921": {
   "t": "town",
   "road": true
  },
  "2922": {
   "t": "mixed",
   "road": true
  },
  "2923": {
   "t": "mixed",
   "road": true
  },
  "2924": {
   "t": "mixed"
  },
  "2925": {
   "t": "mixed",
   "road": true
  },
  "2926": {
   "t": "mixed"
  },
  "2927": {
   "t": "offmap"
  },
  "3000": {
   "t": "offmap"
  },
  "3001": {
   "t": "offmap"
  },
  "3002": {
   "t": "offmap"
  },
  "3003": {
   "t": "offmap"
  },
  "3004": {
   "t": "offmap"
  },
  "3005": {
   "t": "offmap"
  },
  "3006": {
   "t": "broken",
   "road": true
  },
  "3007": {
   "t": "broken",
   "road": true
  },
  "3008": {
   "t": "broken",
   "road": true
  },
  "3009": {
   "t": "mixed",
   "road": true
  },
  "3010": {
   "t": "town",
   "road": true
  },
  "3011": {
   "t": "town",
   "road": true
  },
  "3012": {
   "t": "mixed",
   "road": true
  },
  "3013": {
   "t": "broken"
  },
  "3014": {
   "t": "mixed"
  },
  "3015": {
   "t": "mixed"
  },
  "3016": {
   "t": "woods"
  },
  "3017": {
   "t": "mixed"
  },
  "3018": {
   "t": "mixed",
   "road": true
  },
  "3019": {
   "t": "mixed"
  },
  "3020": {
   "t": "town",
   "road": true
  },
  "3021": {
   "t": "town",
   "road": true
  },
  "3022": {
   "t": "mixed",
   "road": true
  },
  "3023": {
   "t": "mixed",
   "road": true
  },
  "3024": {
   "t": "mixed",
   "road": true
  },
  "3025": {
   "t": "town",
   "road": true
  },
  "3026": {
   "t": "offmap"
  },
  "3027": {
   "t": "offmap"
  },
  "3101": {
   "t": "offmap"
  },
  "3102": {
   "t": "offmap"
  },
  "3103": {
   "t": "offmap"
  },
  "3104": {
   "t": "offmap"
  },
  "3105": {
   "t": "offmap"
  },
  "3106": {
   "t": "mixed"
  },
  "3107": {
   "t": "mixed",
   "road": true
  },
  "3108": {
   "t": "mixed",
   "road": true
  },
  "3109": {
   "t": "mixed",
   "road": true
  },
  "3110": {
   "t": "town",
   "road": true
  },
  "3111": {
   "t": "town"
  },
  "3112": {
   "t": "town"
  },
  "3113": {
   "t": "woods"
  },
  "3114": {
   "t": "woods"
  },
  "3115": {
   "t": "woods"
  },
  "3116": {
   "t": "woods"
  },
  "3117": {
   "t": "broken"
  },
  "3118": {
   "t": "town",
   "road": true
  },
  "3119": {
   "t": "town",
   "road": true
  },
  "3120": {
   "t": "broken"
  },
  "3121": {
   "t": "town",
   "road": true
  },
  "3122": {
   "t": "mixed",
   "road": true
  },
  "3123": {
   "t": "mixed"
  },
  "3124": {
   "t": "town"
  },
  "3125": {
   "t": "mixed"
  },
  "3126": {
   "t": "broken"
  },
  "3127": {
   "t": "offmap"
  },
  "3200": {
   "t": "offmap"
  },
  "3201": {
   "t": "offmap"
  },
  "3202": {
   "t": "offmap"
  },
  "3203": {
   "t": "offmap"
  },
  "3204": {
   "t": "offmap"
  },
  "3205": {
   "t": "offmap"
  },
  "3206": {
   "t": "mixed"
  },
  "3207": {
   "t": "broken"
  },
  "3208": {
   "t": "broken",
   "road": true
  },
  "3209": {
   "t": "broken"
  },
  "3210": {
   "t": "broken",
   "road": true
  },
  "3211": {
   "t": "town",
   "road": true
  },
  "3212": {
   "t": "broken",
   "road": true
  },
  "3213": {
   "t": "broken"
  },
  "3214": {
   "t": "broken"
  },
  "3215": {
   "t": "broken"
  },
  "3216": {
   "t": "broken"
  },
  "3217": {
   "t": "broken"
  },
  "3218": {
   "t": "broken"
  },
  "3219": {
   "t": "broken"
  },
  "3220": {
   "t": "broken"
  },
  "3221": {
   "t": "town",
   "road": true
  },
  "3222": {
   "t": "broken"
  },
  "3223": {
   "t": "mixed",
   "road": true
  },
  "3224": {
   "t": "town"
  },
  "3225": {
   "t": "broken"
  },
  "3226": {
   "t": "offmap"
  },
  "3227": {
   "t": "offmap"
  },
  "3301": {
   "t": "offmap"
  },
  "3302": {
   "t": "offmap"
  },
  "3303": {
   "t": "offmap"
  },
  "3304": {
   "t": "offmap"
  },
  "3305": {
   "t": "offmap"
  },
  "3306": {
   "t": "mixed"
  },
  "3307": {
   "t": "broken",
   "road": true
  },
  "3308": {
   "t": "woods"
  },
  "3309": {
   "t": "mixed",
   "road": true
  },
  "3310": {
   "t": "mixed"
  },
  "3311": {
   "t": "woods"
  },
  "3312": {
   "t": "woods"
  },
  "3313": {
   "t": "woods"
  },
  "3314": {
   "t": "woods"
  },
  "3315": {
   "t": "mixed",
   "road": true
  },
  "3316": {
   "t": "town",
   "road": true
  },
  "3317": {
   "t": "broken"
  },
  "3318": {
   "t": "broken",
   "road": true
  },
  "3319": {
   "t": "broken",
   "road": true
  },
  "3320": {
   "t": "broken"
  },
  "3321": {
   "t": "broken"
  },
  "3322": {
   "t": "town",
   "road": true
  },
  "3323": {
   "t": "mixed",
   "road": true
  },
  "3324": {
   "t": "mixed"
  },
  "3325": {
   "t": "town",
   "road": true
  },
  "3326": {
   "t": "town",
   "road": true
  },
  "3327": {
   "t": "offmap"
  },
  "3400": {
   "t": "offmap"
  },
  "3401": {
   "t": "offmap"
  },
  "3402": {
   "t": "offmap"
  },
  "3403": {
   "t": "offmap"
  },
  "3404": {
   "t": "offmap"
  },
  "3405": {
   "t": "offmap"
  },
  "3406": {
   "t": "mixed"
  },
  "3407": {
   "t": "woods"
  },
  "3408": {
   "t": "broken",
   "road": true
  },
  "3409": {
   "t": "mixed"
  },
  "3410": {
   "t": "broken",
   "road": true
  },
  "3411": {
   "t": "mixed"
  },
  "3412": {
   "t": "town",
   "road": true
  },
  "3413": {
   "t": "mixed",
   "road": true
  },
  "3414": {
   "t": "mixed"
  },
  "3415": {
   "t": "broken",
   "road": true
  },
  "3416": {
   "t": "town"
  },
  "3417": {
   "t": "broken"
  },
  "3418": {
   "t": "mixed"
  },
  "3419": {
   "t": "broken"
  },
  "3420": {
   "t": "broken"
  },
  "3421": {
   "t": "broken",
   "road": true
  },
  "3422": {
   "t": "mixed"
  },
  "3423": {
   "t": "city",
   "road": true
  },
  "3424": {
   "t": "town",
   "road": true
  },
  "3425": {
   "t": "broken"
  },
  "3426": {
   "t": "offmap"
  },
  "3427": {
   "t": "offmap"
  },
  "3501": {
   "t": "offmap"
  },
  "3502": {
   "t": "offmap"
  },
  "3503": {
   "t": "offmap"
  },
  "3504": {
   "t": "offmap"
  },
  "3505": {
   "t": "offmap"
  },
  "3506": {
   "t": "mixed"
  },
  "3507": {
   "t": "broken",
   "road": true
  },
  "3508": {
   "t": "mixed"
  },
  "3509": {
   "t": "town",
   "road": true
  },
  "3510": {
   "t": "broken"
  },
  "3511": {
   "t": "mixed",
   "road": true
  },
  "3512": {
   "t": "town",
   "road": true
  },
  "3513": {
   "t": "rough"
  },
  "3514": {
   "t": "woods"
  },
  "3515": {
   "t": "woods"
  },
  "3516": {
   "t": "town"
  },
  "3517": {
   "t": "town"
  },
  "3518": {
   "t": "town"
  },
  "3519": {
   "t": "rough"
  },
  "3520": {
   "t": "town",
   "road": true
  },
  "3521": {
   "t": "city",
   "road": true
  },
  "3522": {
   "t": "town",
   "road": true
  },
  "3523": {
   "t": "city",
   "road": true
  },
  "3524": {
   "t": "city",
   "road": true
  },
  "3525": {
   "t": "woods"
  },
  "3526": {
   "t": "town"
  },
  "3527": {
   "t": "offmap"
  },
  "3600": {
   "t": "offmap"
  },
  "3601": {
   "t": "offmap"
  },
  "3602": {
   "t": "offmap"
  },
  "3603": {
   "t": "offmap"
  },
  "3604": {
   "t": "offmap"
  },
  "3605": {
   "t": "offmap"
  },
  "3606": {
   "t": "mixed"
  },
  "3607": {
   "t": "broken"
  },
  "3608": {
   "t": "mixed",
   "road": true
  },
  "3609": {
   "t": "mixed",
   "road": true
  },
  "3610": {
   "t": "woods"
  },
  "3611": {
   "t": "woods"
  },
  "3612": {
   "t": "rough"
  },
  "3613": {
   "t": "broken"
  },
  "3614": {
   "t": "mixed"
  },
  "3615": {
   "t": "woods"
  },
  "3616": {
   "t": "woods"
  },
  "3617": {
   "t": "mixed"
  },
  "3618": {
   "t": "woods"
  },
  "3619": {
   "t": "rough"
  },
  "3620": {
   "t": "rough"
  },
  "3621": {
   "t": "rough"
  },
  "3622": {
   "t": "rough"
  },
  "3623": {
   "t": "woods"
  },
  "3624": {
   "t": "woods"
  },
  "3625": {
   "t": "rough"
  },
  "3626": {
   "t": "offmap"
  },
  "3627": {
   "t": "offmap"
  },
  "3701": {
   "t": "offmap"
  },
  "3702": {
   "t": "offmap"
  },
  "3703": {
   "t": "offmap"
  },
  "3704": {
   "t": "offmap"
  },
  "3705": {
   "t": "offmap"
  },
  "3706": {
   "t": "mixed"
  },
  "3707": {
   "t": "mixed"
  },
  "3708": {
   "t": "mixed"
  },
  "3709": {
   "t": "town",
   "road": true
  },
  "3710": {
   "t": "rough"
  },
  "3711": {
   "t": "woods"
  },
  "3712": {
   "t": "broken"
  },
  "3713": {
   "t": "broken",
   "road": true
  },
  "3714": {
   "t": "mixed"
  },
  "3715": {
   "t": "woods"
  },
  "3716": {
   "t": "woods"
  },
  "3717": {
   "t": "mixed"
  },
  "3718": {
   "t": "mixed"
  },
  "3719": {
   "t": "woods"
  },
  "3720": {
   "t": "rough"
  },
  "3721": {
   "t": "rough"
  },
  "3722": {
   "t": "woods"
  },
  "3723": {
   "t": "woods"
  },
  "3724": {
   "t": "woods"
  },
  "3725": {
   "t": "rough"
  },
  "3726": {
   "t": "rough"
  },
  "3727": {
   "t": "offmap"
  },
  "3800": {
   "t": "offmap"
  },
  "3801": {
   "t": "offmap"
  },
  "3802": {
   "t": "offmap"
  },
  "3803": {
   "t": "offmap"
  },
  "3804": {
   "t": "offmap"
  },
  "3805": {
   "t": "offmap"
  },
  "3806": {
   "t": "mixed"
  },
  "3807": {
   "t": "town",
   "road": true
  },
  "3808": {
   "t": "mixed"
  },
  "3809": {
   "t": "rough"
  },
  "3810": {
   "t": "woods"
  },
  "3811": {
   "t": "mixed"
  },
  "3812": {
   "t": "mixed",
   "road": true
  },
  "3813": {
   "t": "broken"
  },
  "3814": {
   "t": "woods"
  },
  "3815": {
   "t": "rough"
  },
  "3816": {
   "t": "woods"
  },
  "3817": {
   "t": "mixed"
  },
  "3818": {
   "t": "mixed"
  },
  "3819": {
   "t": "offmap"
  },
  "3820": {
   "t": "woods"
  },
  "3821": {
   "t": "woods"
  },
  "3822": {
   "t": "rough"
  },
  "3823": {
   "t": "woods"
  },
  "3824": {
   "t": "woods"
  },
  "3825": {
   "t": "woods"
  },
  "3826": {
   "t": "offmap"
  },
  "3827": {
   "t": "offmap"
  },
  "3901": {
   "t": "offmap"
  },
  "3902": {
   "t": "offmap"
  },
  "3903": {
   "t": "offmap"
  },
  "3904": {
   "t": "offmap"
  },
  "3905": {
   "t": "offmap"
  },
  "3906": {
   "t": "mixed"
  },
  "3907": {
   "t": "mixed",
   "road": true
  },
  "3908": {
   "t": "woods"
  },
  "3909": {
   "t": "rough"
  },
  "3910": {
   "t": "woods"
  },
  "3911": {
   "t": "town"
  },
  "3912": {
   "t": "mixed"
  },
  "3913": {
   "t": "mixed"
  },
  "3914": {
   "t": "woods"
  },
  "3915": {
   "t": "woods"
  },
  "3916": {
   "t": "woods"
  },
  "3917": {
   "t": "town"
  },
  "3918": {
   "t": "town",
   "road": true
  },
  "3919": {
   "t": "mixed"
  },
  "3920": {
   "t": "woods"
  },
  "3921": {
   "t": "woods"
  },
  "3922": {
   "t": "rough"
  },
  "3923": {
   "t": "woods"
  },
  "3924": {
   "t": "woods"
  },
  "3925": {
   "t": "woods"
  },
  "3926": {
   "t": "woods"
  },
  "3927": {
   "t": "offmap"
  },
  "4000": {
   "t": "offmap"
  },
  "4001": {
   "t": "offmap"
  },
  "4002": {
   "t": "offmap"
  },
  "4003": {
   "t": "offmap"
  },
  "4004": {
   "t": "offmap"
  },
  "4005": {
   "t": "offmap"
  },
  "4006": {
   "t": "offmap"
  },
  "4007": {
   "t": "offmap"
  },
  "4008": {
   "t": "offmap"
  },
  "4009": {
   "t": "offmap"
  },
  "4010": {
   "t": "offmap"
  },
  "4011": {
   "t": "offmap"
  },
  "4012": {
   "t": "offmap"
  },
  "4013": {
   "t": "offmap"
  },
  "4014": {
   "t": "offmap"
  },
  "4015": {
   "t": "offmap"
  },
  "4016": {
   "t": "offmap"
  },
  "4017": {
   "t": "offmap"
  },
  "4018": {
   "t": "offmap"
  },
  "4019": {
   "t": "offmap"
  },
  "4020": {
   "t": "offmap"
  },
  "4021": {
   "t": "offmap"
  },
  "4022": {
   "t": "offmap"
  },
  "4023": {
   "t": "offmap"
  },
  "4024": {
   "t": "offmap"
  },
  "4025": {
   "t": "offmap"
  },
  "4026": {
   "t": "offmap"
  },
  "4027": {
   "t": "offmap"
  }
 },
 "sides": {
  "0104|0204": {
   "road": "trail"
  },
  "0105|0204": {
   "road": "road"
  },
  "0105|0205": {
   "water": "stream"
  },
  "0106|0205": {
   "water": "stream"
  },
  "0106|0206": {
   "water": "stream"
  },
  "0107|0206": {
   "water": "stream"
  },
  "0107|0207": {
   "water": "stream"
  },
  "0108|0207": {
   "water": "stream"
  },
  "0108|0208": {
   "water": "stream"
  },
  "0109|0208": {
   "water": "stream"
  },
  "0109|0209": {
   "road": "road"
  },
  "0111|0112": {
   "water": "stream"
  },
  "0111|0211": {
   "water": "stream"
  },
  "0117|0216": {
   "road": "road"
  },
  "0203|0304": {
   "road": "trail"
  },
  "0204|0205": {
   "road": "road"
  },
  "0204|0304": {
   "road": "road"
  },
  "0205|0206": {
   "road": "road"
  },
  "0206|0307": {
   "road": "road"
  },
  "0208|0209": {
   "water": "stream"
  },
  "0209|0309": {
   "water": "stream"
  },
  "0209|0310": {
   "road": "road"
  },
  "0210|0211": {
   "water": "stream"
  },
  "0210|0310": {
   "water": "stream"
  },
  "0210|0311": {
   "water": "stream"
  },
  "0214|0215": {
   "road": "road"
  },
  "0216|0316": {
   "road": "trail"
  },
  "0301|0302": {
   "water": "river"
  },
  "0304|0403": {
   "road": "road"
  },
  "0304|0404": {
   "road": "road"
  },
  "0308|0309": {
   "road": "road"
  },
  "0308|0407": {
   "road": "road"
  },
  "0309|0310": {
   "road": "road"
  },
  "0310|0311": {
   "water": "stream",
   "road": "road",
   "bridge": true,
   "bridge_type": "highway",
   "crossing": true
  },
  "0311|0312": {
   "road": "trail"
  },
  "0311|0410": {
   "water": "stream"
  },
  "0403|0503": {
   "road": "road"
  },
  "0404|0505": {
   "road": "road"
  },
  "0407|0507": {
   "road": "road"
  },
  "0410|0411": {
   "water": "stream"
  },
  "0410|0511": {
   "water": "stream"
  },
  "0413|0414": {
   "road": "road"
  },
  "0414|0514": {
   "road": "trail"
  },
  "0415|0516": {
   "road": "trail"
  },
  "0501|0601": {
   "water": "stream"
  },
  "0502|0601": {
   "water": "stream"
  },
  "0502|0602": {
   "water": "stream"
  },
  "0503|0602": {
   "road": "road"
  },
  "0503|0603": {
   "water": "stream",
   "bridge": true,
   "bridge_type": "canal",
   "crossing": true,
   "road": "road"
  },
  "0504|0603": {
   "water": "stream"
  },
  "0504|0604": {
   "water": "stream"
  },
  "0505|0604": {
   "water": "stream"
  },
  "0505|0605": {
   "water": "stream",
   "road": "road",
   "bridge": true,
   "bridge_type": "canal",
   "crossing": true
  },
  "0506|0605": {
   "water": "stream"
  },
  "0506|0606": {
   "water": "stream"
  },
  "0507|0606": {
   "water": "stream"
  },
  "0507|0607": {
   "water": "stream"
  },
  "0508|0607": {
   "water": "stream"
  },
  "0508|0608": {
   "water": "stream"
  },
  "0509|0608": {
   "water": "stream"
  },
  "0509|0609": {
   "water": "stream"
  },
  "0510|0511": {
   "water": "stream"
  },
  "0510|0609": {
   "water": "stream"
  },
  "0510|0610": {
   "water": "stream"
  },
  "0511|0610": {
   "water": "stream"
  },
  "0516|0616": {
   "road": "road"
  },
  "0523|0622": {
   "road": "trail"
  },
  "0523|0623": {
   "road": "road"
  },
  "0608|0708": {
   "road": "road"
  },
  "0610|0611": {
   "water": "stream"
  },
  "0610|0711": {
   "water": "stream"
  },
  "0613|0713": {
   "road": "trail"
  },
  "0622|0722": {
   "road": "road"
  },
  "0702|0802": {
   "road": "trail"
  },
  "0706|0805": {
   "road": "road"
  },
  "0710|0711": {
   "water": "stream",
   "road": "trail",
   "bridge": true,
   "bridge_type": "canal",
   "crossing": true
  },
  "0710|0810": {
   "water": "stream"
  },
  "0711|0712": {
   "road": "trail"
  },
  "0713|0812": {
   "road": "road"
  },
  "0716|0816": {
   "water": "river"
  },
  "0802|0803": {
   "road": "trail"
  },
  "0803|0903": {
   "road": "road"
  },
  "0805|0806": {
   "road": "road"
  },
  "0805|0905": {
   "road": "road"
  },
  "0809|0810": {
   "water": "stream"
  },
  "0809|0910": {
   "water": "stream"
  },
  "0812|0912": {
   "road": "road"
  },
  "0817|0918": {
   "road": "road"
  },
  "0820|0920": {
   "road": "trail"
  },
  "0825|0926": {
   "water": "river"
  },
  "0905|1004": {
   "road": "road"
  },
  "0909|0910": {
   "water": "stream"
  },
  "0909|1008": {
   "water": "river"
  },
  "0909|1009": {
   "water": "stream"
  },
  "0912|1011": {
   "road": "road"
  },
  "0913|0914": {
   "road": "road"
  },
  "0915|0916": {
   "road": "road"
  },
  "0920|1019": {
   "road": "trail"
  },
  "0925|0926": {
   "water": "river"
  },
  "0925|1025": {
   "water": "river"
  },
  "1003|1103": {
   "road": "road"
  },
  "1004|1005": {
   "road": "trail"
  },
  "1004|1105": {
   "road": "road"
  },
  "1005|1106": {
   "road": "trail"
  },
  "1008|1009": {
   "water": "stream"
  },
  "1008|1108": {
   "water": "river"
  },
  "1008|1109": {
   "water": "stream"
  },
  "1018|1019": {
   "road": "road"
  },
  "1018|1119": {
   "road": "trail"
  },
  "1019|1120": {
   "road": "trail"
  },
  "1024|1025": {
   "water": "river"
  },
  "1024|1125": {
   "water": "river"
  },
  "1103|1202": {
   "road": "trail"
  },
  "1105|1204": {
   "road": "road"
  },
  "1106|1206": {
   "road": "road"
  },
  "1108|1109": {
   "water": "stream"
  },
  "1108|1208": {
   "water": "stream"
  },
  "1124|1125": {
   "water": "river"
  },
  "1124|1224": {
   "water": "river"
  },
  "1204|1305": {
   "road": "road"
  },
  "1206|1306": {
   "road": "trail"
  },
  "1206|1307": {
   "water": "stream",
   "bridge": true,
   "bridge_type": "rail",
   "crossing": true
  },
  "1207|1208": {
   "water": "stream"
  },
  "1207|1307": {
   "water": "stream"
  },
  "1207|1308": {
   "road": "trail",
   "water": "stream",
   "bridge": true,
   "bridge_type": "canal",
   "crossing": true
  },
  "1208|1209": {
   "road": "road"
  },
  "1209|1309": {
   "road": "trail"
  },
  "1221|1322": {
   "road": "trail"
  },
  "1223|1224": {
   "water": "river"
  },
  "1223|1324": {
   "water": "river"
  },
  "1305|1306": {
   "road": "trail"
  },
  "1306|1307": {
   "water": "stream"
  },
  "1306|1406": {
   "water": "stream"
  },
  "1308|1407": {
   "road": "road"
  },
  "1309|1409": {
   "road": "trail"
  },
  "1312|1412": {
   "road": "trail"
  },
  "1323|1324": {
   "water": "river"
  },
  "1323|1423": {
   "water": "river"
  },
  "1405|1406": {
   "water": "stream"
  },
  "1405|1506": {
   "water": "stream"
  },
  "1412|1413": {
   "road": "trail"
  },
  "1417|1418": {
   "road": "trail"
  },
  "1422|1423": {
   "road": "trail",
   "bridge": true,
   "bridge_type": "highway",
   "crossing": true
  },
  "1423|1523": {
   "water": "river"
  },
  "1423|1524": {
   "road": "road"
  },
  "1502|1601": {
   "road": "trail"
  },
  "1504|1604": {
   "water": "stream"
  },
  "1505|1506": {
   "water": "stream"
  },
  "1505|1604": {
   "water": "stream"
  },
  "1505|1605": {
   "water": "stream"
  },
  "1511|1610": {
   "road": "road"
  },
  "1516|1616": {
   "road": "road"
  },
  "1517|1518": {
   "road": "road"
  },
  "1517|1617": {
   "road": "trail"
  },
  "1519|1520": {
   "road": "road"
  },
  "1520|1620": {
   "road": "road"
  },
  "1523|1524": {
   "water": "river",
   "bridge": true,
   "bridge_type": "rail",
   "crossing": true
  },
  "1523|1623": {
   "water": "river"
  },
  "1524|1623": {
   "road": "road"
  },
  "1603|1604": {
   "water": "stream"
  },
  "1603|1704": {
   "water": "stream"
  },
  "1610|1710": {
   "road": "road"
  },
  "1616|1717": {
   "road": "trail"
  },
  "1622|1623": {
   "water": "river"
  },
  "1622|1723": {
   "water": "river"
  },
  "1623|1723": {
   "road": "road"
  },
  "1702|1802": {
   "water": "stream"
  },
  "1703|1704": {
   "water": "stream"
  },
  "1703|1802": {
   "water": "stream"
  },
  "1703|1803": {
   "water": "stream"
  },
  "1704|1803": {
   "road": "trail"
  },
  "1710|1809": {
   "road": "road"
  },
  "1713|1714": {
   "road": "road"
  },
  "1713|1813": {
   "road": "road"
  },
  "1721|1821": {
   "water": "river"
  },
  "1722|1723": {
   "water": "river"
  },
  "1722|1821": {
   "water": "river"
  },
  "1722|1822": {
   "water": "river"
  },
  "1801|1802": {
   "water": "stream"
  },
  "1801|1901": {
   "water": "stream"
  },
  "1801|1902": {
   "water": "stream"
  },
  "1802|1803": {
   "road": "trail"
  },
  "1802|1902": {
   "road": "trail"
  },
  "1813|1914": {
   "road": "road"
  },
  "1815|1916": {
   "road": "road"
  },
  "1817|1818": {
   "road": "road"
  },
  "1820|1821": {
   "water": "river"
  },
  "1820|1921": {
   "water": "river"
  },
  "1824|1825": {
   "water": "river"
  },
  "1824|1925": {
   "water": "river"
  },
  "1914|2013": {
   "road": "road"
  },
  "1920|1921": {
   "water": "river"
  },
  "1920|2020": {
   "water": "river",
   "bridge": true,
   "bridge_type": "rail",
   "crossing": true
  },
  "1921|2020": {
   "road": "trail"
  },
  "1924|2023": {
   "road": "road"
  },
  "1925|2024": {
   "water": "river"
  },
  "2003|2004": {
   "road": "trail"
  },
  "2008|2109": {
   "road": "trail"
  },
  "2012|2013": {
   "road": "road"
  },
  "2012|2112": {
   "road": "road"
  },
  "2016|2116": {
   "road": "road"
  },
  "2016|2117": {
   "water": "river"
  },
  "2017|2117": {
   "water": "river"
  },
  "2017|2118": {
   "water": "river"
  },
  "2018|2118": {
   "water": "river"
  },
  "2018|2119": {
   "water": "river"
  },
  "2019|2020": {
   "water": "river"
  },
  "2019|2119": {
   "water": "river"
  },
  "2019|2120": {
   "water": "river"
  },
  "2020|2120": {
   "water": "stream"
  },
  "2020|2121": {
   "road": "trail"
  },
  "2109|2208": {
   "road": "road"
  },
  "2112|2211": {
   "road": "road"
  },
  "2114|2115": {
   "road": "road"
  },
  "2114|2213": {
   "road": "trail"
  },
  "2114|2214": {
   "water": "river"
  },
  "2115|2116": {
   "road": "road"
  },
  "2115|2214": {
   "water": "river"
  },
  "2116|2117": {
   "water": "river"
  },
  "2116|2215": {
   "road": "road"
  },
  "2116|2216": {
   "water": "river"
  },
  "2117|2216": {
   "water": "river"
  },
  "2119|2120": {
   "road": "road"
  },
  "2120|2121": {
   "road": "road",
   "water": "stream",
   "bridge": true,
   "bridge_type": "canal",
   "crossing": true
  },
  "2120|2220": {
   "water": "stream"
  },
  "2121|2122": {
   "road": "road"
  },
  "2121|2220": {
   "road": "trail"
  },
  "2123|2222": {
   "water": "river"
  },
  "2123|2223": {
   "road": "trail"
  },
  "2201|2301": {
   "water": "river"
  },
  "2208|2308": {
   "road": "road"
  },
  "2211|2311": {
   "road": "road"
  },
  "2213|2214": {
   "water": "river"
  },
  "2213|2313": {
   "road": "road"
  },
  "2214|2215": {
   "water": "river"
  },
  "2214|2314": {
   "water": "river"
  },
  "2214|2315": {
   "water": "river"
  },
  "2215|2216": {
   "water": "river"
  },
  "2215|2315": {
   "water": "river"
  },
  "2215|2316": {
   "water": "river"
  },
  "2216|2217": {
   "water": "river"
  },
  "2217|2218": {
   "road": "trail"
  },
  "2218|2318": {
   "road": "road"
  },
  "2219|2220": {
   "road": "road",
   "water": "stream",
   "bridge": true,
   "bridge_type": "canal",
   "crossing": true
  },
  "2219|2320": {
   "water": "stream"
  },
  "2222|2223": {
   "road": "road"
  },
  "2222|2322": {
   "water": "river"
  },
  "2301|2302": {
   "water": "river"
  },
  "2302|2401": {
   "water": "river"
  },
  "2302|2402": {
   "road": "road"
  },
  "2308|2407": {
   "road": "road"
  },
  "2308|2408": {
   "road": "road"
  },
  "2310|2311": {
   "road": "trail"
  },
  "2313|2412": {
   "road": "road"
  },
  "2313|2413": {
   "water": "river"
  },
  "2314|2315": {
   "water": "river"
  },
  "2314|2413": {
   "water": "river"
  },
  "2314|2414": {
   "water": "river"
  },
  "2319|2320": {
   "water": "stream"
  },
  "2319|2419": {
   "water": "stream",
   "road": "trail",
   "bridge": true,
   "bridge_type": "canal",
   "crossing": true
  },
  "2324|2423": {
   "road": "road"
  },
  "2401|2402": {
   "water": "river"
  },
  "2402|2503": {
   "water": "river"
  },
  "2403|2503": {
   "water": "river"
  },
  "2403|2504": {
   "road": "road"
  },
  "2407|2507": {
   "road": "road"
  },
  "2408|2508": {
   "road": "road"
  },
  "2413|2513": {
   "water": "river",
   "bridge": true,
   "bridge_type": "rail",
   "crossing": true
  },
  "2414|2415": {
   "road": "road"
  },
  "2415|2515": {
   "road": "road"
  },
  "2417|2518": {
   "road": "trail"
  },
  "2418|2419": {
   "water": "stream"
  },
  "2418|2519": {
   "water": "stream"
  },
  "2423|2523": {
   "road": "road"
  },
  "2503|2504": {
   "water": "river"
  },
  "2503|2603": {
   "water": "river"
  },
  "2504|2603": {
   "water": "river"
  },
  "2505|2506": {
   "road": "road"
  },
  "2505|2605": {
   "water": "river"
  },
  "2506|2507": {
   "road": "road"
  },
  "2506|2605": {
   "water": "river"
  },
  "2506|2606": {
   "water": "river"
  },
  "2507|2508": {
   "road": "road"
  },
  "2507|2606": {
   "water": "river"
  },
  "2508|2509": {
   "road": "road"
  },
  "2508|2608": {
   "water": "river"
  },
  "2509|2608": {
   "water": "river"
  },
  "2509|2609": {
   "water": "river"
  },
  "2510|2609": {
   "water": "river"
  },
  "2512|2611": {
   "road": "trail"
  },
  "2512|2612": {
   "water": "river"
  },
  "2513|2514": {
   "water": "river"
  },
  "2513|2612": {
   "water": "river"
  },
  "2513|2613": {
   "water": "river"
  },
  "2515|2614": {
   "road": "road"
  },
  "2518|2519": {
   "water": "stream",
   "bridge": true,
   "bridge_type": "canal",
   "crossing": true,
   "road": "road"
  },
  "2518|2618": {
   "water": "river"
  },
  "2519|2618": {
   "water": "stream"
  },
  "2519|2619": {
   "road": "trail"
  },
  "2520|2620": {
   "road": "road"
  },
  "2521|2620": {
   "road": "trail"
  },
  "2521|2621": {
   "road": "trail"
  },
  "2603|2604": {
   "water": "river"
  },
  "2604|2605": {
   "water": "river"
  },
  "2604|2704": {
   "water": "river"
  },
  "2604|2705": {
   "water": "river"
  },
  "2606|2607": {
   "water": "river"
  },
  "2607|2608": {
   "water": "river"
  },
  "2607|2707": {
   "water": "river"
  },
  "2607|2708": {
   "water": "river"
  },
  "2609|2610": {
   "water": "river"
  },
  "2610|2611": {
   "road": "road"
  },
  "2610|2710": {
   "water": "river",
   "road": "trail"
  },
  "2610|2711": {
   "water": "river"
  },
  "2611|2612": {
   "water": "river"
  },
  "2611|2711": {
   "water": "river"
  },
  "2611|2712": {
   "water": "river"
  },
  "2612|2712": {
   "road": "trail"
  },
  "2614|2714": {
   "road": "road"
  },
  "2618|2619": {
   "water": "stream"
  },
  "2618|2719": {
   "water": "river"
  },
  "2619|2620": {
   "road": "trail"
  },
  "2619|2719": {
   "water": "stream"
  },
  "2620|2621": {
   "road": "road"
  },
  "2620|2721": {
   "water": "river"
  },
  "2621|2721": {
   "water": "river",
   "road": "road",
   "bridge": true,
   "bridge_type": "highway",
   "crossing": true
  },
  "2623|2624": {
   "road": "road"
  },
  "2623|2724": {
   "water": "river",
   "road": "trail"
  },
  "2624|2625": {
   "road": "road"
  },
  "2624|2724": {
   "water": "river"
  },
  "2624|2725": {
   "water": "river"
  },
  "2625|2725": {
   "water": "river"
  },
  "2704|2803": {
   "water": "river"
  },
  "2704|2804": {
   "water": "river"
  },
  "2705|2804": {
   "water": "river"
  },
  "2711|2712": {
   "road": "trail"
  },
  "2719|2720": {
   "water": "stream"
  },
  "2719|2819": {
   "water": "river"
  },
  "2720|2721": {
   "water": "river"
  },
  "2720|2819": {
   "water": "river"
  },
  "2720|2820": {
   "water": "river"
  },
  "2721|2722": {
   "water": "river",
   "road": "trail",
   "bridge": true,
   "bridge_type": "highway",
   "crossing": true
  },
  "2721|2820": {
   "road": "road"
  },
  "2722|2821": {
   "water": "river"
  },
  "2722|2822": {
   "water": "river"
  },
  "2723|2724": {
   "water": "river"
  },
  "2723|2822": {
   "water": "river"
  },
  "2723|2823": {
   "water": "river"
  },
  "2725|2726": {
   "water": "river"
  },
  "2726|2825": {
   "water": "river"
  },
  "2804|2805": {
   "water": "river"
  },
  "2816|2917": {
   "water": "river"
  },
  "2817|2917": {
   "water": "river"
  },
  "2817|2918": {
   "water": "river"
  },
  "2818|2819": {
   "water": "river"
  },
  "2818|2918": {
   "water": "river"
  },
  "2818|2919": {
   "water": "river"
  },
  "2823|2824": {
   "road": "trail"
  },
  "2825|2925": {
   "road": "road"
  },
  "2825|2926": {
   "water": "river"
  },
  "2908|3007": {
   "road": "trail"
  },
  "2915|3015": {
   "water": "river"
  },
  "2916|2917": {
   "water": "river"
  },
  "2916|3015": {
   "water": "river"
  },
  "2916|3016": {
   "water": "river"
  },
  "2920|3020": {
   "road": "trail"
  },
  "2921|3021": {
   "road": "trail"
  },
  "2923|3022": {
   "road": "road"
  },
  "2925|2926": {
   "water": "river"
  },
  "2925|3024": {
   "road": "road"
  },
  "2925|3025": {
   "water": "river"
  },
  "3006|3007": {
   "road": "road"
  },
  "3006|3106": {
   "water": "river"
  },
  "3006|3107": {
   "water": "river"
  },
  "3007|3008": {
   "road": "road"
  },
  "3007|3107": {
   "water": "river"
  },
  "3007|3108": {
   "water": "river"
  },
  "3008|3009": {
   "road": "road"
  },
  "3008|3108": {
   "water": "river"
  },
  "3008|3109": {
   "water": "river"
  },
  "3009|3010": {
   "road": "road"
  },
  "3009|3109": {
   "water": "river"
  },
  "3009|3110": {
   "water": "river"
  },
  "3010|3011": {
   "road": "road"
  },
  "3010|3110": {
   "water": "river"
  },
  "3010|3111": {
   "water": "river"
  },
  "3011|3012": {
   "road": "road"
  },
  "3011|3111": {
   "water": "river"
  },
  "3011|3112": {
   "water": "river",
   "road": "trail"
  },
  "3012|3112": {
   "water": "river"
  },
  "3012|3113": {
   "water": "river"
  },
  "3013|3113": {
   "water": "river"
  },
  "3013|3114": {
   "water": "river"
  },
  "3014|3015": {
   "water": "river"
  },
  "3014|3114": {
   "water": "river"
  },
  "3014|3115": {
   "water": "river"
  },
  "3021|3022": {
   "road": "road"
  },
  "3021|3121": {
   "road": "trail"
  },
  "3021|3122": {
   "road": "road"
  },
  "3024|3025": {
   "water": "river"
  },
  "3024|3125": {
   "water": "river"
  },
  "3108|3109": {
   "road": "road"
  },
  "3109|3110": {
   "road": "road"
  },
  "3118|3119": {
   "road": "trail"
  },
  "3119|3120": {
   "road": "road"
  },
  "3120|3121": {
   "road": "road"
  },
  "3124|3125": {
   "water": "river",
   "ferry": true,
   "crossing": true
  },
  "3125|3224": {
   "water": "river"
  },
  "3207|3307": {
   "road": "road"
  },
  "3208|3308": {
   "road": "trail"
  },
  "3211|3212": {
   "road": "road"
  },
  "3212|3213": {
   "road": "road"
  },
  "3213|3314": {
   "road": "trail"
  },
  "3216|3316": {
   "road": "road"
  },
  "3224|3225": {
   "water": "river"
  },
  "3224|3325": {
   "water": "river"
  },
  "3225|3325": {
   "road": "road"
  },
  "3307|3407": {
   "road": "road"
  },
  "3312|3412": {
   "water": "river"
  },
  "3313|3412": {
   "water": "river"
  },
  "3313|3413": {
   "water": "river"
  },
  "3314|3315": {
   "road": "trail"
  },
  "3314|3413": {
   "water": "river"
  },
  "3314|3414": {
   "water": "river"
  },
  "3315|3414": {
   "water": "river"
  },
  "3316|3415": {
   "road": "road"
  },
  "3317|3417": {
   "road": "trail"
  },
  "3318|3319": {
   "road": "trail"
  },
  "3318|3418": {
   "water": "river"
  },
  "3319|3418": {
   "water": "river"
  },
  "3319|3419": {
   "road": "trail"
  },
  "3322|3323": {
   "road": "road"
  },
  "3322|3421": {
   "road": "road"
  },
  "3323|3423": {
   "water": "river",
   "road": "road",
   "bridge": true,
   "bridge_type": "highway",
   "crossing": true
  },
  "3324|3325": {
   "water": "river"
  },
  "3324|3423": {
   "water": "river"
  },
  "3324|3424": {
   "water": "river"
  },
  "3325|3424": {
   "water": "river",
   "road": "trail",
   "bridge": true,
   "bridge_type": "highway",
   "crossing": true
  },
  "3325|3425": {
   "water": "river",
   "road": "trail",
   "bridge": true,
   "bridge_type": "highway",
   "crossing": true
  },
  "3326|3425": {
   "water": "river"
  },
  "3407|3408": {
   "road": "trail"
  },
  "3407|3507": {
   "road": "trail"
  },
  "3410|3511": {
   "water": "river"
  },
  "3411|3412": {
   "water": "river"
  },
  "3411|3511": {
   "water": "river"
  },
  "3412|3413": {
   "road": "road"
  },
  "3412|3512": {
   "road": "road"
  },
  "3412|3513": {
   "road": "trail"
  },
  "3414|3415": {
   "water": "river"
  },
  "3415|3515": {
   "water": "river"
  },
  "3415|3516": {
   "water": "river"
  },
  "3416|3516": {
   "water": "river"
  },
  "3416|3517": {
   "water": "river"
  },
  "3417|3418": {
   "water": "river"
  },
  "3417|3517": {
   "water": "river"
  },
  "3417|3518": {
   "water": "river"
  },
  "3418|3419": {
   "water": "river"
  },
  "3418|3519": {
   "water": "river"
  },
  "3419|3420": {
   "road": "road"
  },
  "3419|3519": {
   "water": "river"
  },
  "3419|3520": {
   "water": "river"
  },
  "3420|3421": {
   "road": "road"
  },
  "3420|3520": {
   "water": "river",
   "ferry": true,
   "crossing": true
  },
  "3420|3521": {
   "water": "river"
  },
  "3421|3521": {
   "water": "river"
  },
  "3421|3522": {
   "water": "river"
  },
  "3422|3423": {
   "water": "river"
  },
  "3422|3522": {
   "water": "river",
   "bridge": true,
   "bridge_type": "rail",
   "crossing": true
  },
  "3422|3523": {
   "water": "river"
  },
  "3423|3424": {
   "road": "road"
  },
  "3423|3523": {
   "road": "trail"
  },
  "3423|3524": {
   "road": "trail"
  },
  "3509|3608": {
   "road": "trail"
  },
  "3509|3609": {
   "water": "river"
  },
  "3510|3511": {
   "water": "river"
  },
  "3510|3609": {
   "water": "river"
  },
  "3510|3610": {
   "water": "river"
  },
  "3518|3617": {
   "road": "road"
  },
  "3519|3520": {
   "road": "trail"
  },
  "3521|3522": {
   "road": "road"
  },
  "3522|3523": {
   "road": "road"
  },
  "3523|3524": {
   "road": "trail"
  },
  "3524|3525": {
   "road": "road"
  },
  "3524|3624": {
   "road": "road"
  },
  "3525|3526": {
   "road": "trail"
  },
  "3606|3706": {
   "water": "river"
  },
  "3606|3707": {
   "water": "river"
  },
  "3607|3608": {
   "road": "road"
  },
  "3607|3707": {
   "water": "river"
  },
  "3607|3708": {
   "water": "river"
  },
  "3608|3609": {
   "water": "river"
  },
  "3608|3708": {
   "water": "river"
  },
  "3608|3709": {
   "water": "river",
   "ferry": true,
   "crossing": true
  },
  "3609|3709": {
   "road": "trail"
  },
  "3613|3713": {
   "road": "road"
  },
  "3616|3617": {
   "road": "trail"
  },
  "3622|3623": {
   "road": "trail"
  },
  "3713|3812": {
   "road": "road"
  },
  "3807|3808": {
   "road": "trail"
  },
  "3807|3907": {
   "road": "trail"
  },
  "2619|2720": {
   "water": "stream",
   "road": "trail",
   "bridge": true,
   "bridge_type": "canal",
   "crossing": true
  },
  "2216|2316": {
   "water": "river",
   "road": "road",
   "bridge": true,
   "bridge_type": "highway",
   "crossing": true
  },
  "3411|3512": {
   "water": "river",
   "bridge": true,
   "bridge_type": "rail",
   "crossing": true
  }
 },
 "provenance": {
  "base": "ref/terrain.json (legacy validated extraction)",
  "corrections": "build_terrain.py 2026-07-11 eye-verified pass (see module docstring)",
  "rail_suspects": [
   "1921|2020",
   "2020|2121",
   "2121|2220",
   "2119|2120",
   "1206|1306",
   "1305|1306",
   "3119|3120",
   "3120|3121",
   "3118|3119",
   "2920|3020",
   "2921|3021",
   "3021|3121",
   "3317|3417",
   "3318|3319",
   "3319|3419",
   "1524|1623"
  ]
 }
}